data/release_analysis_prompt.j2
github_overlord/__init__.py
github_overlord/config.py
github_overlord/patch.py
github_overlord/release_checker.py
github_overlord/stale_commenter.py
github_overlord/utils.py
github_overlord-0.8.0.dist-info/LICENSE.md
github_overlord-0.8.0.dist-info/METADATA
github_overlord-0.8.0.dist-info/WHEEL
github_overlord-0.8.0.dist-info/entry_points.txt
github_overlord-0.8.0.dist-info/RECORD
