Metadata-Version: 2.1
Name: github-overlord
Version: 0.8.0
Summary: Automatically merge Dependabot PRs in public repositories
Home-page: https://github.com/iloveitaly/github-overlord
Keywords: github,dependabot,automation
Author: Michael Bianco
Author-email: mike@mikebian.co
Requires-Python: >=3.11,<4.0
Classifier: Programming Language :: Python :: 3
Classifier: Programming Language :: Python :: 3.11
Classifier: Programming Language :: Python :: 3.12
Requires-Dist: apscheduler (>=3.10.4,<4.0.0)
Requires-Dist: click (>=8.1.7,<9.0.0)
Requires-Dist: funcy-pipe (>=0.11.1,<0.15.0)
Requires-Dist: jinja2 (>=3.1.0,<4.0.0)
Requires-Dist: openai (>=1.52.2,<3.0.0)
Requires-Dist: pydantic-ai-slim[google] (>=0.0.18,<0.0.19)
Requires-Dist: pygithub (>=2.4.0,<3.0.0)
Requires-Dist: python-decouple-typed (>=3.11.0,<4.0.0)
Requires-Dist: structlog (>=24.4,<26.0)
